MANIFEST.in
README.md
cirrus.conf
requirements.txt
setup.py
src/cirrus/_2to3.py
src/cirrus/__init__.py
src/cirrus/build.py
src/cirrus/builder_plugin.py
src/cirrus/chef_tools.py
src/cirrus/cirrus_setup.py
src/cirrus/conda_utils.py
src/cirrus/configuration.py
src/cirrus/creds_plugin.py
src/cirrus/delegate.py
src/cirrus/deploy.py
src/cirrus/deploy_plugins.py
src/cirrus/docker.py
src/cirrus/docs.py
src/cirrus/documentation_utils.py
src/cirrus/editor_plugin.py
src/cirrus/environment.py
src/cirrus/fabric_helpers.py
src/cirrus/feature.py
src/cirrus/git_tools.py
src/cirrus/gitconfig.py
src/cirrus/github_tools.py
src/cirrus/hello.py
src/cirrus/invoke_helpers.py
src/cirrus/linter_plugin.py
src/cirrus/logger.py
src/cirrus/package.py
src/cirrus/package_container.py
src/cirrus/plusone.py
src/cirrus/prestage.py
src/cirrus/publish_plugins.py
src/cirrus/pylint_tools.py
src/cirrus/pypirc.py
src/cirrus/quality_control.py
src/cirrus/release.py
src/cirrus/release_status.py
src/cirrus/release_utils.py
src/cirrus/req_utils.py
src/cirrus/review.py
src/cirrus/scp.py
src/cirrus/selfupdate.py
src/cirrus/test.py
src/cirrus/twine_helpers.py
src/cirrus/upload_plugins.py
src/cirrus/utils.py
src/cirrus/plugins/__init__.py
src/cirrus/plugins/jenkins.py
src/cirrus/plugins/builders/__init__.py
src/cirrus/plugins/builders/conda.py
src/cirrus/plugins/builders/conda_env.py
src/cirrus/plugins/builders/conda_pip.py
src/cirrus/plugins/builders/venv_pip.py
src/cirrus/plugins/creds/__init__.py
src/cirrus/plugins/creds/default.py
src/cirrus/plugins/creds/keyring.py
src/cirrus/plugins/deployers/__init__.py
src/cirrus/plugins/deployers/chef.py
src/cirrus/plugins/editors/__init__.py
src/cirrus/plugins/editors/sublime.py
src/cirrus/plugins/linters/__init__.py
src/cirrus/plugins/linters/coverage_linter.py
src/cirrus/plugins/linters/pep8_linter.py
src/cirrus/plugins/linters/pyflakes_linter.py
src/cirrus/plugins/linters/pylint_linter.py
src/cirrus/plugins/publishers/__init__.py
src/cirrus_cli.egg-info/PKG-INFO
src/cirrus_cli.egg-info/SOURCES.txt
src/cirrus_cli.egg-info/dependency_links.txt
src/cirrus_cli.egg-info/entry_points.txt
src/cirrus_cli.egg-info/requires.txt
src/cirrus_cli.egg-info/top_level.txt