Metadata-Version: 1.0
Name: cirrus-cli
Version: 0.2.42
Summary: cirrus development and build git extensions
Home-page: https://github.com/evansde77/cirrus
Author: Dave Evans
Author-email: evansde77@gmail.com
License: UNKNOWN
Platform: UNKNOWN
